README.md
setup.py
staticjam/__init__.py
staticjam/__main__.py
staticjam/staticjam.py
staticjam.egg-info/PKG-INFO
staticjam.egg-info/SOURCES.txt
staticjam.egg-info/dependency_links.txt
staticjam.egg-info/entry_points.txt
staticjam.egg-info/requires.txt
staticjam.egg-info/top_level.txt