Metadata-Version: 1.0
Name: staticjam
Version: 4.2.0
Summary: markdown + jinja, static site generator
Home-page: UNKNOWN
Author: SlimeMaid
Author-email: SlimeMaid@gmail.com
License: UNKNOWN
Keywords: cli
Platform: UNKNOWN
